{
    "input_path": "D:\\09.Work\\65.Interop\\04.task\\30.GBTasks\\codes\\github\\GBObjectDetection/Datas/Testing\\PUA_QM05.png",
    "boxes": [
        {
            "cls_id": 4,
            "label": "U1_QM2",
            "score": 0.9994114637374878,
            "coordinate": [
                49.073238372802734,
                136.07070922851562,
                125.14643096923828,
                151.1739959716797
            ]
        },
        {
            "cls_id": 5,
            "label": "U2_QM1",
            "score": 0.9978905320167542,
            "coordinate": [
                126.74972534179688,
                136.88975524902344,
                201.54647827148438,
                151.99038696289062
            ]
        },
        {
            "cls_id": 6,
            "label": "U3_QM2",
            "score": 0.9965770840644836,
            "coordinate": [
                201.29946899414062,
                135.6032257080078,
                279.58349609375,
                151.50218200683594
            ]
        }
    ]
}