{
  "version": "5.5.0",
  "flags": {},
  "shapes": [
    {
      "label": "000_rt",
      "points": [
        [
          115.59090909090912,
          100.70454545454547
        ],
        [
          125.81818181818186,
          113.77272727272728
        ]
      ],
      "group_id": null,
      "description": "",
      "shape_type": "rectangle",
      "flags": {},
      "mask": null
    },
    {
      "label": "101_U1",
      "points": [
        [
          645.7045454545455,
          255.25
        ],
        [
          664.0980392156863,
          269.17973856209153
        ]
      ],
      "group_id": null,
      "description": "",
      "shape_type": "rectangle",
      "flags": {},
      "mask": null
    },
    {
      "label": "102_U2",
      "points": [
        [
          703.6590909090909,
          256.3863636363636
        ],
        [
          724.2287581699347,
          269.17973856209153
        ]
      ],
      "group_id": null,
      "description": "",
      "shape_type": "rectangle",
      "flags": {},
      "mask": null
    },
    {
      "label": "103_U3",
      "points": [
        [
          794.0,
          254.11363636363637
        ],
        [
          813.1176470588235,
          270.48692810457516
        ]
      ],
      "group_id": null,
      "description": "",
      "shape_type": "rectangle",
      "flags": {},
      "mask": null
    },
    {
      "label": "101_U1",
      "points": [
        [
          345.7045454545455,
          430.8181818181818
        ],
        [
          364.0980392156863,
          444.9967320261438
        ]
      ],
      "group_id": null,
      "description": "",
      "shape_type": "rectangle",
      "flags": {},
      "mask": null
    },
    {
      "label": "102_U2",
      "points": [
        [
          436.04545454545456,
          430.25
        ],
        [
          458.21568627450984,
          446.30392156862746
        ]
      ],
      "group_id": null,
      "description": "",
      "shape_type": "rectangle",
      "flags": {},
      "mask": null
    },
    {
      "label": "103_U3",
      "points": [
        [
          526.3863636363636,
          430.8181818181818
        ],
        [
          545.7973856209151,
          446.30392156862746
        ]
      ],
      "group_id": null,
      "description": "",
      "shape_type": "rectangle",
      "flags": {},
      "mask": null
    }
  ],
  "imagePath": "..\\images\\01_rt\\01_rt_image004.png",
  "imageData": null,
  "imageHeight": 473,
  "imageWidth": 938
}