{
  "version": "5.5.0",
  "flags": {},
  "shapes": [
    {
      "label": "000_rt",
      "points": [
        [
          174.31227436823104,
          64.22924187725631
        ],
        [
          183.69855595667872,
          78.3086642599278
        ]
      ],
      "group_id": null,
      "description": "",
      "shape_type": "rectangle",
      "flags": {},
      "mask": null
    },
    {
      "label": "000_rt",
      "points": [
        [
          233.15703971119135,
          121.99097472924187
        ],
        [
          242.9043321299639,
          134.26534296028882
        ]
      ],
      "group_id": null,
      "description": "",
      "shape_type": "rectangle",
      "flags": {},
      "mask": null
    },
    {
      "label": "104_YI",
      "points": [
        [
          160.11825726141078,
          64.60373443983404
        ],
        [
          173.81120331950206,
          79.12655601659752
        ]
      ],
      "group_id": null,
      "description": null,
      "shape_type": "rectangle",
      "flags": {},
      "mask": null
    },
    {
      "label": "106_DA",
      "points": [
        [
          182.91176470588235,
          62.58823529411765
        ],
        [
          197.91176470588235,
          79.64705882352942
        ]
      ],
      "group_id": null,
      "description": "",
      "shape_type": "rectangle",
      "flags": {},
      "mask": null
    },
    {
      "label": "104_YI",
      "points": [
        [
          219.6764705882353,
          120.5294117647059
        ],
        [
          233.2058823529412,
          136.11764705882354
        ]
      ],
      "group_id": null,
      "description": "",
      "shape_type": "rectangle",
      "flags": {},
      "mask": null
    },
    {
      "label": "106_DA",
      "points": [
        [
          242.61764705882354,
          119.94117647058825
        ],
        [
          256.1470588235294,
          138.1764705882353
        ]
      ],
      "group_id": null,
      "description": "",
      "shape_type": "rectangle",
      "flags": {},
      "mask": null
    }
  ],
  "imagePath": "..\\images\\01_rt\\01_rt_image083.png",
  "imageData": null,
  "imageHeight": 179,
  "imageWidth": 597
}