{
  "version": "5.5.0",
  "flags": {},
  "shapes": [
    {
      "label": "000_rt",
      "points": [
        [
          171.90780911062905,
          80.36334056399133
        ],
        [
          181.4522776572668,
          95.5477223427332
        ]
      ],
      "group_id": null,
      "description": "",
      "shape_type": "rectangle",
      "flags": {},
      "mask": null
    },
    {
      "label": "102_U2",
      "points": [
        [
          195.3351409978308,
          135.67787418655095
        ],
        [
          213.53990024937656,
          149.61970074812967
        ]
      ],
      "group_id": null,
      "description": "",
      "shape_type": "rectangle",
      "flags": {},
      "mask": null
    },
    {
      "label": "103_U3",
      "points": [
        [
          262.79718004338395,
          135.89479392624727
        ],
        [
          280.3728179551122,
          150.11845386533668
        ]
      ],
      "group_id": null,
      "description": "",
      "shape_type": "rectangle",
      "flags": {},
      "mask": null
    },
    {
      "label": "101_U1",
      "points": [
        [
          127.65618221258133,
          135.89479392624727
        ],
        [
          144.4625935162095,
          151.11596009975062
        ]
      ],
      "group_id": null,
      "description": "",
      "shape_type": "rectangle",
      "flags": {},
      "mask": null
    },
    {
      "label": "000_rt",
      "points": [
        [
          78.63232104121474,
          137.41323210412148
        ],
        [
          88.39370932754879,
          149.56073752711495
        ]
      ],
      "group_id": null,
      "description": "",
      "shape_type": "rectangle",
      "flags": {},
      "mask": null
    },
    {
      "label": "000_rt",
      "points": [
        [
          88.17678958785248,
          136.97939262472883
        ],
        [
          98.37201735357917,
          150.42841648590021
        ]
      ],
      "group_id": null,
      "description": "",
      "shape_type": "rectangle",
      "flags": {},
      "mask": null
    },
    {
      "label": "000_rt",
      "points": [
        [
          98.58893709327548,
          136.76247288503254
        ],
        [
          107.91648590021691,
          150.6453362255965
        ]
      ],
      "group_id": null,
      "description": "",
      "shape_type": "rectangle",
      "flags": {},
      "mask": null
    },
    {
      "label": "000_rt",
      "points": [
        [
          108.13340563991322,
          136.5455531453362
        ],
        [
          117.46095444685466,
          150.2114967462039
        ]
      ],
      "group_id": null,
      "description": "",
      "shape_type": "rectangle",
      "flags": {},
      "mask": null
    },
    {
      "label": "000_rt",
      "points": [
        [
          117.46095444685466,
          136.97939262472883
        ],
        [
          127.22234273318871,
          150.86225596529283
        ]
      ],
      "group_id": null,
      "description": "",
      "shape_type": "rectangle",
      "flags": {},
      "mask": null
    },
    {
      "label": "000_rt",
      "points": [
        [
          146.3112798264642,
          136.76247288503254
        ],
        [
          155.63882863340564,
          149.99457700650757
        ]
      ],
      "group_id": null,
      "description": "",
      "shape_type": "rectangle",
      "flags": {},
      "mask": null
    },
    {
      "label": "000_rt",
      "points": [
        [
          155.85574837310193,
          136.97939262472883
        ],
        [
          165.8340563991323,
          150.6453362255965
        ]
      ],
      "group_id": null,
      "description": "",
      "shape_type": "rectangle",
      "flags": {},
      "mask": null
    },
    {
      "label": "000_rt",
      "points": [
        [
          165.8340563991323,
          137.19631236442515
        ],
        [
          175.37852494577004,
          151.9468546637744
        ]
      ],
      "group_id": null,
      "description": "",
      "shape_type": "rectangle",
      "flags": {},
      "mask": null
    },
    {
      "label": "000_rt",
      "points": [
        [
          175.37852494577004,
          136.3286334056399
        ],
        [
          185.35683297180043,
          152.380694143167
        ]
      ],
      "group_id": null,
      "description": "",
      "shape_type": "rectangle",
      "flags": {},
      "mask": null
    },
    {
      "label": "000_rt",
      "points": [
        [
          185.35683297180043,
          136.1117136659436
        ],
        [
          195.11822125813447,
          152.1637744034707
        ]
      ],
      "group_id": null,
      "description": "",
      "shape_type": "rectangle",
      "flags": {},
      "mask": null
    },
    {
      "label": "000_rt",
      "points": [
        [
          213.99023861171364,
          136.5455531453362
        ],
        [
          223.96854663774403,
          150.86225596529283
        ]
      ],
      "group_id": null,
      "description": "",
      "shape_type": "rectangle",
      "flags": {},
      "mask": null
    },
    {
      "label": "000_rt",
      "points": [
        [
          224.18546637744032,
          136.97939262472883
        ],
        [
          233.29609544468545,
          151.07917570498915
        ]
      ],
      "group_id": null,
      "description": "",
      "shape_type": "rectangle",
      "flags": {},
      "mask": null
    },
    {
      "label": "000_rt",
      "points": [
        [
          233.72993492407807,
          137.41323210412148
        ],
        [
          243.05748373101952,
          150.6453362255965
        ]
      ],
      "group_id": null,
      "description": "",
      "shape_type": "rectangle",
      "flags": {},
      "mask": null
    },
    {
      "label": "000_rt",
      "points": [
        [
          242.62364425162687,
          136.3286334056399
        ],
        [
          252.81887201735356,
          151.07917570498915
        ]
      ],
      "group_id": null,
      "description": "",
      "shape_type": "rectangle",
      "flags": {},
      "mask": null
    },
    {
      "label": "000_rt",
      "points": [
        [
          253.03579175704988,
          136.1117136659436
        ],
        [
          262.146420824295,
          150.6453362255965
        ]
      ],
      "group_id": null,
      "description": "",
      "shape_type": "rectangle",
      "flags": {},
      "mask": null
    },
    {
      "label": "104_YI",
      "points": [
        [
          158.1783042394015,
          80.04364089775561
        ],
        [
          171.39526184538656,
          95.75436408977555
        ]
      ],
      "group_id": null,
      "description": "",
      "shape_type": "rectangle",
      "flags": {},
      "mask": null
    },
    {
      "label": "106_DA",
      "points": [
        [
          181.86907730673317,
          80.54239401496258
        ],
        [
          195.5847880299252,
          96.25311720698254
        ]
      ],
      "group_id": null,
      "description": "",
      "shape_type": "rectangle",
      "flags": {},
      "mask": null
    }
  ],
  "imagePath": "..\\images\\01_rt\\01_rt_image110.png",
  "imageData": null,
  "imageHeight": 195,
  "imageWidth": 359
}