{
    "version": "5.5.0",
    "flags": {},
    "shapes": [
        {
            "label": "U1_QM2",
            "points": [
                [
                    336,
                    324
                ],
                [
                    406,
                    338
                ]
            ],
            "group_id": null,
            "description": "",
            "shape_type": "rectangle",
            "flags": {},
            "mask": null
        },
        {
            "label": "U2_QM1",
            "points": [
                [
                    407,
                    324
                ],
                [
                    476,
                    338
                ]
            ],
            "group_id": null,
            "description": "",
            "shape_type": "rectangle",
            "flags": {},
            "mask": null
        },
        {
            "label": "U3_QM2",
            "points": [
                [
                    477,
                    324
                ],
                [
                    546,
                    338
                ]
            ],
            "group_id": null,
            "description": "",
            "shape_type": "rectangle",
            "flags": {},
            "mask": null
        }
    ],
    "imagePath": "..\\images\\QM0221\\05_6rec_image176_0_2_0221.jpg",
    "imageData": null,
    "imageHeight": 499,
    "imageWidth": 665
}