{
    "input_path": "D:\\09.Work\\65.Interop\\04.task\\30.GBTasks\\codes\\github\\GBObjectDetection/Datas/Testing\\others_1780432_PUA_OneDrive2.png",
    "boxes": [
        {
            "cls_id": 0,
            "label": "U1_Tag1",
            "score": 0.9971613883972168,
            "coordinate": [
                98.4298324584961,
                268.0635070800781,
                178.39410400390625,
                286.0852966308594
            ]
        },
        {
            "cls_id": 0,
            "label": "U1_Tag1",
            "score": 0.5507065057754517,
            "coordinate": [
                216.64913940429688,
                245.7906036376953,
                280.62188720703125,
                263.19891357421875
            ]
        },
        {
            "cls_id": 1,
            "label": "U2_Tag1",
            "score": 0.9980118274688721,
            "coordinate": [
                180.87918090820312,
                267.69732666015625,
                257.0490417480469,
                286.4673767089844
            ]
        },
        {
            "cls_id": 1,
            "label": "U2_Tag1",
            "score": 0.8538387417793274,
            "coordinate": [
                218.35205078125,
                245.550537109375,
                278.9022216796875,
                264.9696044921875
            ]
        },
        {
            "cls_id": 1,
            "label": "U2_Tag1",
            "score": 0.9477306008338928,
            "coordinate": [
                281.18841552734375,
                245.2181854248047,
                345.9032897949219,
                265.3616943359375
            ]
        },
        {
            "cls_id": 2,
            "label": "U3_Tag1",
            "score": 0.9970952272415161,
            "coordinate": [
                347.9270935058594,
                244.61277770996094,
                408.84283447265625,
                264.2651672363281
            ]
        }
    ]
}